<?xml version="1.0" encoding="UTF-8"?>
<DEFECTS>
  <DEFECT>
    <SFA>
      <FILEPATH>C:\dev\ConstraintPhysics\ConstraintPhysics\src\</FILEPATH>
      <FILENAME>AABB.h</FILENAME>
      <LINE>20</LINE>
      <COLUMN>9</COLUMN>
    </SFA>
    <DEFECTCODE>26498</DEFECTCODE>
    <DESCRIPTION>The function 'std::numeric_limits&lt;double&gt;::infinity' is constexpr, mark variable 'inf' constexpr if compile-time evaluation is desired (con.5).</DESCRIPTION>
    <FUNCTION>AABB::combine</FUNCTION>
    <DECORATED>?combine@AABB@@SA?AU1@AEBV?$vector@UAABB@@V?$allocator@UAABB@@@std@@@std@@@Z</DECORATED>
    <FUNCLINE>15</FUNCLINE>
    <PATH></PATH>
  </DEFECT>
</DEFECTS>